SmaDataManagerMClient/__init__.py
SmaDataManagerMClient/base_client.py
SmaDataManagerMClient/client.py
SmaDataManagerMClient/known_channels.py
SmaDataManagerMClient/model.py
SmaDataManagerMClient/test/__init__.py
SmaDataManagerMClient/test/http_response_mock.py
SmaDataManagerMClient/test/test_AuthTokenInfo.py
SmaDataManagerMClient/test/test_ChannelValues.py
SmaDataManagerMClient/test/test_ComponentInfo.py
SmaDataManagerMClient/test/test_LiveMeasurementQueryItem.py
SmaDataManagerMClient/test/test_TimeValuePair.py
SmaDataManagerMClient/test/test_client.py
SmaDataManagerMClient/test/test_known_channels.py
SmaDataManagerMClient-0.0.2.dist-info/LICENSE
SmaDataManagerMClient-0.0.2.dist-info/METADATA
SmaDataManagerMClient-0.0.2.dist-info/WHEEL
SmaDataManagerMClient-0.0.2.dist-info/top_level.txt
SmaDataManagerMClient-0.0.2.dist-info/RECORD
