Metadata-Version: 2.1
Name: SmaDataManagerMClient
Version: 0.0.2
Summary: SmaDataManagerMClient
Home-page: https://github.com/Tabisch/SMA_Data_Manager_M_Client
Author: Tabisch
Author-email: tobithieman@gmail.com
Project-URL: Bug Tracker, https://github.com/Tabisch/SMA_Data_Manager_M_Client/issues
Classifier: Programming Language :: Python :: 3
Classifier: License :: OSI Approved :: MIT License
Classifier: Operating System :: OS Independent
Requires-Python: >=3.11
License-File: LICENSE
